llmwerewolf_rs/__init__.py
llmwerewolf_rs-0.0.2.dist-info/WHEEL
llmwerewolf_rs-0.0.2.dist-info/entry_points.txt
llmwerewolf_rs-0.0.2.dist-info/METADATA
llmwerewolf_rs-0.0.2.dist-info/RECORD
