Metadata-Version: 2.3
Name: llmwerewolf-rs
Version: 0.0.2
Summary: Python wrapper for the LLM Werewolf Rust binary.
Keywords: cli,ai,werewolf,llm
Author: Wei Lee
Author-email: Wei Lee <mai@mai0313.com>
License: MIT
Classifier: License :: OSI Approved :: MIT License
Classifier: Programming Language :: Python :: 3
Classifier: Programming Language :: Python :: 3.8
Classifier: Programming Language :: Python :: 3.9
Classifier: Programming Language :: Python :: 3.10
Classifier: Programming Language :: Python :: 3.11
Classifier: Programming Language :: Python :: 3.12
Requires-Python: >=3.8
Project-URL: Bug Tracker, https://github.com/Mai0313/LLMWereWolf-rs/issues
Project-URL: Homepage, https://github.com/Mai0313/LLMWereWolf-rs
Project-URL: Repository, https://github.com/Mai0313/LLMWereWolf-rs
